raven_appengine.py
setup.py
raven_appengine.egg-info/PKG-INFO
raven_appengine.egg-info/SOURCES.txt
raven_appengine.egg-info/dependency_links.txt
raven_appengine.egg-info/not-zip-safe
raven_appengine.egg-info/top_level.txt