Metadata-Version: 1.1
Name: raven-appengine
Version: 0.0.1
Summary: A raven transport that uses the appengine deferred library.
Home-page: http://github.com/danielchatfield/raven-appengine
Author: Daniel Chatfield
Author-email: chatfielddaniel@gmail.com
License: UNKNOWN
Platform: UNKNOWN
Classifier: License :: OSI Approved :: MIT License
Classifier: Programming Language :: Python
